.pypyreadme
MANIFEST.in
README.md
VERSION
pyrightconfig.json
requirements.txt
setup.cfg
setup.py
bin/pyquanda-cmd
samples/interview.yaml
samples/ansible_test/fail_module/config.yaml
samples/ansible_test/fail_module/vars.yaml
samples/ansible_test/fail_module/handlers/main.yaml
samples/ansible_test/fail_module/tasks/main.yaml
samples/ansible_test/ok_module/config.yaml
samples/ansible_test/ok_module/vars.yaml
samples/ansible_test/ok_module/handlers/main.yaml
samples/ansible_test/ok_module/tasks/main.yaml
samples/hook_samples/slack_webhook.yaml
samples/host_setup/config.yaml
samples/host_setup/vars.yaml
samples/host_setup/handlers/main.yaml
samples/host_setup/tasks/dump_ec2.yaml
samples/host_setup/tasks/main.yaml
samples/host_setup/tasks/ntp.yaml
samples/host_setup/tasks/restricted_sudo.yaml
samples/host_setup/tasks/system.yaml
samples/host_setup/tasks/usersetup.yaml
samples/host_setup/tasks/xonsh.yaml
samples/host_setup/templates/hosts.j2
samples/host_setup/templates/ntp.conf.j2
samples/host_setup/templates/xonrc.j2
samples/slack_templates/ansible_event.j2.json
samples/slack_templates/questionable_activity.j2.json
samples/slack_templates/runbook_complete.j2.json
samples/slack_templates/xonsh_answer.j2.json
samples/slack_templates/xonsh_command.j2.json
src/pyquanda/__init__.py
src/pyquanda/environment.py
src/pyquanda/exceptions.py
src/pyquanda.egg-info/PKG-INFO
src/pyquanda.egg-info/SOURCES.txt
src/pyquanda.egg-info/dependency_links.txt
src/pyquanda.egg-info/requires.txt
src/pyquanda.egg-info/top_level.txt
src/pyquanda/ansible/__init__.py
src/pyquanda/ansible/play.yaml
src/pyquanda/cli/__init__.py
src/pyquanda/cli/subcommands.py
src/pyquanda/cli/templates.py
src/pyquanda/cli/data/common/vars.yaml
src/pyquanda/cli/data/common/handler/main.yaml
src/pyquanda/cli/data/common/tasks/main.yaml
src/pyquanda/cli/data/intro/config.yaml
src/pyquanda/cli/data/intro/templates/err.j2
src/pyquanda/cli/data/intro/templates/welcome.j2
src/pyquanda/cli/data/problem/config.yaml
src/pyquanda/cli/data/system/config.yaml
src/pyquanda/demo/mock_config.yaml
src/pyquanda/demo/demo_questions/config.yaml
src/pyquanda/demo/demo_questions/handlers/main.yaml
