Metadata-Version: 2.1
Name: pyquanda
Version: 1.0.20
Summary: Python Interview environment
Home-page: https://github.com/shollingsworth/pyquanda
Author: Steven Hollingsworth
Author-email: hollingsworth.stevend@gmail.com
License: MIT
Project-URL: Changes, https://github.com/shollingsworth/pyquanda/blob/main/CHANGELOG.md
Project-URL: Source Code, https://github.com/shollingsworth/pyquanda
Project-URL: Issue Tracker, https://github.com/shollingsworth/pyquanda/issues/
Project-URL: Twitter, https://twitter.com/_stevo
Project-URL: Documentation, https://shollingsworth.github.io/pyquanda/index.html
Keywords: interview,environment
Platform: UNKNOWN
Classifier: Development Status :: 5 - Production/Stable
Classifier: Environment :: Console
Classifier: Intended Audience :: Developers
Classifier: License :: OSI Approved :: MIT License
Classifier: Intended Audience :: End Users/Desktop
Classifier: Intended Audience :: Information Technology
Classifier: Operating System :: OS Independent
Classifier: Programming Language :: Python :: 3 :: Only
Classifier: Programming Language :: Python :: 3.7
Classifier: Programming Language :: Python :: 3.8
Classifier: Programming Language :: Python :: 3.9
Classifier: Programming Language :: Python :: 3.10
Requires-Python: >=3.7
Provides-Extra: ansible
